hindsight_embed/__init__.py
hindsight_embed/cli.py
hindsight_embed/daemon_client.py
hindsight_embed-0.4.7.dist-info/METADATA
hindsight_embed-0.4.7.dist-info/WHEEL
hindsight_embed-0.4.7.dist-info/entry_points.txt
hindsight_embed-0.4.7.dist-info/RECORD
