Metadata-Version: 2.4
Name: hindsight-embed
Version: 0.4.7
Summary: Hindsight embedded CLI - local memory operations without a server
Requires-Python: >=3.11
Requires-Dist: httpx>=0.27.0
